melke/EntityRelation.py
melke/__init__.py
MELKE-1.dist-info/METADATA
MELKE-1.dist-info/WHEEL
MELKE-1.dist-info/top_level.txt
MELKE-1.dist-info/RECORD
